vindi/__init__.py
vindi/api.py
vindi/resource.py
vindi-1.0.0.dist-info/LICENSE
vindi-1.0.0.dist-info/METADATA
vindi-1.0.0.dist-info/WHEEL
vindi-1.0.0.dist-info/top_level.txt
vindi-1.0.0.dist-info/RECORD
