Metadata-Version: 2.1
Name: vindi
Version: 1.0.0
Summary: Integração com API da Vindi (Python 3.6+)
Home-page: https://github.com/allisson/python-vindi
Author: Allisson Azevedo
Author-email: allisson@gmail.com
License: UNKNOWN
Keywords: rest client http vindi
Platform: UNKNOWN
Classifier: Development Status :: 3 - Alpha
Classifier: Intended Audience :: Developers
Classifier: Programming Language :: Python :: 3.6
Classifier: Programming Language :: Python :: 3.7
Classifier: Topic :: Software Development :: Libraries
Requires-Dist: simple-rest-client (>=1.0.0)
